{
  "groups": [
    {
      "name": "project",
      "type": "com.hkh.config.WebMvcConfig",
      "sourceType": "com.hkh.config.WebMvcConfig"
    },
    {
      "name": "shiro",
      "type": "com.hkh.config.shiro.ShiroAutoConfiguration",
      "sourceType": "com.hkh.config.shiro.ShiroAutoConfiguration"
    }
  ],
  "properties": [
    {
      "name": "project.headimageurl",
      "type": "java.lang.String",
      "sourceType": "com.hkh.config.WebMvcConfig"
    },
    {
      "name": "project.ueditorfile",
      "type": "java.lang.String",
      "sourceType": "com.hkh.config.WebMvcConfig"
    },
    {
      "name": "project.ueditorimage",
      "type": "java.lang.String",
      "sourceType": "com.hkh.config.WebMvcConfig"
    },
    {
      "name": "project.ueditorpath",
      "type": "java.lang.String",
      "sourceType": "com.hkh.config.WebMvcConfig"
    },
    {
      "name": "project.ueditorvideo",
      "type": "java.lang.String",
      "sourceType": "com.hkh.config.WebMvcConfig"
    },
    {
      "name": "shiro.anons-urls",
      "type": "java.lang.String[]",
      "sourceType": "com.hkh.config.shiro.ShiroAutoConfiguration"
    },
    {
      "name": "shiro.authc-urls",
      "type": "java.lang.String[]",
      "sourceType": "com.hkh.config.shiro.ShiroAutoConfiguration"
    },
    {
      "name": "shiro.hash-algorithm",
      "type": "java.lang.String",
      "sourceType": "com.hkh.config.shiro.ShiroAutoConfiguration",
      "defaultValue": "MD5"
    },
    {
      "name": "shiro.hash-iterations",
      "type": "java.lang.Integer",
      "sourceType": "com.hkh.config.shiro.ShiroAutoConfiguration",
      "defaultValue": 2
    },
    {
      "name": "shiro.login-url",
      "type": "java.lang.String",
      "sourceType": "com.hkh.config.shiro.ShiroAutoConfiguration",
      "defaultValue": "\/index.html"
    },
    {
      "name": "shiro.logout-url",
      "type": "java.lang.String",
      "sourceType": "com.hkh.config.shiro.ShiroAutoConfiguration"
    }
  ],
  "hints": []
}